[
    {
        "Hardware": "AMD Ryzen 7 7840HS w/ Radeon 780M Graphics",
        "Name": "CPU Core #1",
        "Type": "Load",
        "Value": 5.462157726287842
    },
    {
        "Hardware": "AMD Ryzen 7 7840HS w/ Radeon 780M Graphics",
        "Name": "CPU Core #2",
        "Type": "Load",
        "Value": 4.448967933654785
    },
    {
        "Hardware": "AMD Ryzen 7 7840HS w/ Radeon 780M Graphics",
        "Name": "CPU Core #3",
        "Type": "Load",
        "Value": 74.09187316894531
    },
    {
        "Hardware": "AMD Ryzen 7 7840HS w/ Radeon 780M Graphics",
        "Name": "CPU Core #4",
        "Type": "Load",
        "Value": 63.73069763183594
    },
    {
        "Hardware": "AMD Ryzen 7 7840HS w/ Radeon 780M Graphics",
        "Name": "CPU Core #5",
        "Type": "Load",
        "Value": 15.209293365478516
    },
    {
        "Hardware": "AMD Ryzen 7 7840HS w/ Radeon 780M Graphics",
        "Name": "CPU Core #6",
        "Type": "Load",
        "Value": 13.98472785949707
    },
    {
        "Hardware": "AMD Ryzen 7 7840HS w/ Radeon 780M Graphics",
        "Name": "CPU Core #7",
        "Type": "Load",
        "Value": 68.81590270996094
    },
    {
        "Hardware": "AMD Ryzen 7 7840HS w/ Radeon 780M Graphics",
        "Name": "CPU Core #8",
        "Type": "Load",
        "Value": 62.76305389404297
    },
    {
        "Hardware": "AMD Ryzen 7 7840HS w/ Radeon 780M Graphics",
        "Name": "CPU Core #9",
        "Type": "Load",
        "Value": 54.413963317871094
    },
    {
        "Hardware": "AMD Ryzen 7 7840HS w/ Radeon 780M Graphics",
        "Name": "CPU Core #10",
        "Type": "Load",
        "Value": 52.559532165527344
    },
    {
        "Hardware": "AMD Ryzen 7 7840HS w/ Radeon 780M Graphics",
        "Name": "CPU Core #11",
        "Type": "Load",
        "Value": 61.939544677734375
    },
    {
        "Hardware": "AMD Ryzen 7 7840HS w/ Radeon 780M Graphics",
        "Name": "CPU Core #12",
        "Type": "Load",
        "Value": 52.0268440246582
    },
    {
        "Hardware": "AMD Ryzen 7 7840HS w/ Radeon 780M Graphics",
        "Name": "CPU Core #13",
        "Type": "Load",
        "Value": 65.82231140136719
    },
    {
        "Hardware": "AMD Ryzen 7 7840HS w/ Radeon 780M Graphics",
        "Name": "CPU Core #14",
        "Type": "Load",
        "Value": 55.05589294433594
    },
    {
        "Hardware": "AMD Ryzen 7 7840HS w/ Radeon 780M Graphics",
        "Name": "CPU Core #15",
        "Type": "Load",
        "Value": 65.53445434570312
    },
    {
        "Hardware": "AMD Ryzen 7 7840HS w/ Radeon 780M Graphics",
        "Name": "CPU Core #16",
        "Type": "Load",
        "Value": 55.699764251708984
    },
    {
        "Hardware": "AMD Ryzen 7 7840HS w/ Radeon 780M Graphics",
        "Name": "CPU Total",
        "Type": "Load",
        "Value": 48.222434997558594
    },
    {
        "Hardware": "AMD Ryzen 7 7840HS w/ Radeon 780M Graphics",
        "Name": "CPU Core Max",
        "Type": "Load",
        "Value": 74.09187316894531
    },
    {
        "Hardware": "AMD Ryzen 7 7840HS w/ Radeon 780M Graphics",
        "Name": "Package",
        "Type": "Power",
        "Value": 12.45266056060791
    },
    {
        "Hardware": "AMD Ryzen 7 7840HS w/ Radeon 780M Graphics",
        "Name": "Core #1",
        "Type": "Clock",
        "Value": 1143.346923828125
    },
    {
        "Hardware": "AMD Ryzen 7 7840HS w/ Radeon 780M Graphics",
        "Name": "Core #1",
        "Type": "Factor",
        "Value": 11.454545021057129
    },
    {
        "Hardware": "AMD Ryzen 7 7840HS w/ Radeon 780M Graphics",
        "Name": "Core #1 (SMU)",
        "Type": "Power",
        "Value": 0.05871567502617836
    },
    {
        "Hardware": "AMD Ryzen 7 7840HS w/ Radeon 780M Graphics",
        "Name": "Core #1 VID",
        "Type": "Voltage",
        "Value": 0.9624999761581421
    },
    {
        "Hardware": "AMD Ryzen 7 7840HS w/ Radeon 780M Graphics",
        "Name": "Core #2",
        "Type": "Clock",
        "Value": 1143.346923828125
    },
    {
        "Hardware": "AMD Ryzen 7 7840HS w/ Radeon 780M Graphics",
        "Name": "Core #2",
        "Type": "Factor",
        "Value": 11.454545021057129
    },
    {
        "Hardware": "AMD Ryzen 7 7840HS w/ Radeon 780M Graphics",
        "Name": "Core #2 (SMU)",
        "Type": "Power",
        "Value": 0.7349642515182495
    },
    {
        "Hardware": "AMD Ryzen 7 7840HS w/ Radeon 780M Graphics",
        "Name": "Core #2 VID",
        "Type": "Voltage",
        "Value": 0.9624999761581421
    },
    {
        "Hardware": "AMD Ryzen 7 7840HS w/ Radeon 780M Graphics",
        "Name": "Core #3",
        "Type": "Clock",
        "Value": 1143.346923828125
    },
    {
        "Hardware": "AMD Ryzen 7 7840HS w/ Radeon 780M Graphics",
        "Name": "Core #3",
        "Type": "Factor",
        "Value": 11.454545021057129
    },
    {
        "Hardware": "AMD Ryzen 7 7840HS w/ Radeon 780M Graphics",
        "Name": "Core #3 (SMU)",
        "Type": "Power",
        "Value": 0.1501556634902954
    },
    {
        "Hardware": "AMD Ryzen 7 7840HS w/ Radeon 780M Graphics",
        "Name": "Core #3 VID",
        "Type": "Voltage",
        "Value": 0.9624999761581421
    },
    {
        "Hardware": "AMD Ryzen 7 7840HS w/ Radeon 780M Graphics",
        "Name": "Core #4",
        "Type": "Clock",
        "Value": 1143.346923828125
    },
    {
        "Hardware": "AMD Ryzen 7 7840HS w/ Radeon 780M Graphics",
        "Name": "Core #4",
        "Type": "Factor",
        "Value": 11.454545021057129
    },
    {
        "Hardware": "AMD Ryzen 7 7840HS w/ Radeon 780M Graphics",
        "Name": "Core #4 (SMU)",
        "Type": "Power",
        "Value": 0.7257671356201172
    },
    {
        "Hardware": "AMD Ryzen 7 7840HS w/ Radeon 780M Graphics",
        "Name": "Core #4 VID",
        "Type": "Voltage",
        "Value": 0.9624999761581421
    },
    {
        "Hardware": "AMD Ryzen 7 7840HS w/ Radeon 780M Graphics",
        "Name": "Core #5",
        "Type": "Clock",
        "Value": 1143.346923828125
    },
    {
        "Hardware": "AMD Ryzen 7 7840HS w/ Radeon 780M Graphics",
        "Name": "Core #5",
        "Type": "Factor",
        "Value": 11.454545021057129
    },
    {
        "Hardware": "AMD Ryzen 7 7840HS w/ Radeon 780M Graphics",
        "Name": "Core #5 (SMU)",
        "Type": "Power",
        "Value": 0.5937431454658508
    },
    {
        "Hardware": "AMD Ryzen 7 7840HS w/ Radeon 780M Graphics",
        "Name": "Core #5 VID",
        "Type": "Voltage",
        "Value": 0.9624999761581421
    },
    {
        "Hardware": "AMD Ryzen 7 7840HS w/ Radeon 780M Graphics",
        "Name": "Core #6",
        "Type": "Clock",
        "Value": 1143.346923828125
    },
    {
        "Hardware": "AMD Ryzen 7 7840HS w/ Radeon 780M Graphics",
        "Name": "Core #6",
        "Type": "Factor",
        "Value": 11.454545021057129
    },
    {
        "Hardware": "AMD Ryzen 7 7840HS w/ Radeon 780M Graphics",
        "Name": "Core #6 (SMU)",
        "Type": "Power",
        "Value": 0.6577810645103455
    },
    {
        "Hardware": "AMD Ryzen 7 7840HS w/ Radeon 780M Graphics",
        "Name": "Core #6 VID",
        "Type": "Voltage",
        "Value": 0.9624999761581421
    },
    {
        "Hardware": "AMD Ryzen 7 7840HS w/ Radeon 780M Graphics",
        "Name": "Core #7",
        "Type": "Clock",
        "Value": 1143.346923828125
    },
    {
        "Hardware": "AMD Ryzen 7 7840HS w/ Radeon 780M Graphics",
        "Name": "Core #7",
        "Type": "Factor",
        "Value": 11.454545021057129
    },
    {
        "Hardware": "AMD Ryzen 7 7840HS w/ Radeon 780M Graphics",
        "Name": "Core #7 (SMU)",
        "Type": "Power",
        "Value": 0.6753918528556824
    },
    {
        "Hardware": "AMD Ryzen 7 7840HS w/ Radeon 780M Graphics",
        "Name": "Core #7 VID",
        "Type": "Voltage",
        "Value": 0.9624999761581421
    },
    {
        "Hardware": "AMD Ryzen 7 7840HS w/ Radeon 780M Graphics",
        "Name": "Core #8",
        "Type": "Clock",
        "Value": 1143.346923828125
    },
    {
        "Hardware": "AMD Ryzen 7 7840HS w/ Radeon 780M Graphics",
        "Name": "Core #8",
        "Type": "Factor",
        "Value": 11.454545021057129
    },
    {
        "Hardware": "AMD Ryzen 7 7840HS w/ Radeon 780M Graphics",
        "Name": "Core #8 (SMU)",
        "Type": "Power",
        "Value": 0.6751758456230164
    },
    {
        "Hardware": "AMD Ryzen 7 7840HS w/ Radeon 780M Graphics",
        "Name": "Core #8 VID",
        "Type": "Voltage",
        "Value": 0.9624999761581421
    },
    {
        "Hardware": "AMD Ryzen 7 7840HS w/ Radeon 780M Graphics",
        "Name": "Core (Tctl/Tdie)",
        "Type": "Temperature",
        "Value": 43.25000762939453
    },
    {
        "Hardware": "AMD Ryzen 7 7840HS w/ Radeon 780M Graphics",
        "Name": "Core (SVI2 TFN)",
        "Type": "Voltage",
        "Value": 1.5499999523162842
    },
    {
        "Hardware": "AMD Ryzen 7 7840HS w/ Radeon 780M Graphics",
        "Name": "SoC (SVI2 TFN)",
        "Type": "Voltage",
        "Value": 1.5499999523162842
    },
    {
        "Hardware": "AMD Ryzen 7 7840HS w/ Radeon 780M Graphics",
        "Name": "Bus Speed",
        "Type": "Clock",
        "Value": 99.81600189208984
    },
    {
        "Hardware": "Generic Memory",
        "Name": "Memory Used",
        "Type": "Data",
        "Value": 9.04305648803711
    },
    {
        "Hardware": "Generic Memory",
        "Name": "Memory Available",
        "Type": "Data",
        "Value": 18.766380310058594
    },
    {
        "Hardware": "Generic Memory",
        "Name": "Memory",
        "Type": "Load",
        "Value": 32.5179443359375
    },
    {
        "Hardware": "Generic Memory",
        "Name": "Virtual Memory Used",
        "Type": "Data",
        "Value": 13.803497314453125
    },
    {
        "Hardware": "Generic Memory",
        "Name": "Virtual Memory Available",
        "Type": "Data",
        "Value": 18.505939483642578
    },
    {
        "Hardware": "Generic Memory",
        "Name": "Virtual Memory",
        "Type": "Load",
        "Value": 42.722801208496094
    },
    {
        "Hardware": "AMD Radeon(TM) 780M",
        "Name": "GPU Memory Total",
        "Type": "SmallData",
        "Value": 4096.0
    },
    {
        "Hardware": "AMD Radeon(TM) 780M",
        "Name": "Fullscreen FPS",
        "Type": "Factor",
        "Value": 0.0
    },
    {
        "Hardware": "AMD Radeon(TM) 780M",
        "Name": "D3D Dedicated Memory Total",
        "Type": "SmallData",
        "Value": 3949.22265625
    },
    {
        "Hardware": "AMD Radeon(TM) 780M",
        "Name": "D3D Dedicated Memory Free",
        "Type": "SmallData",
        "Value": 2238.3671875
    },
    {
        "Hardware": "AMD Radeon(TM) 780M",
        "Name": "D3D Dedicated Memory Used",
        "Type": "SmallData",
        "Value": 1710.85546875
    },
    {
        "Hardware": "AMD Radeon(TM) 780M",
        "Name": "D3D Shared Memory Used",
        "Type": "SmallData",
        "Value": 648.83984375
    },
    {
        "Hardware": "AMD Radeon(TM) 780M",
        "Name": "D3D Shared Memory Free",
        "Type": "SmallData",
        "Value": 13589.591796875
    },
    {
        "Hardware": "AMD Radeon(TM) 780M",
        "Name": "D3D Shared Memory Total",
        "Type": "SmallData",
        "Value": 14238.431640625
    },
    {
        "Hardware": "AMD Radeon(TM) 780M",
        "Name": "D3D 3D",
        "Type": "Load",
        "Value": 3.065218687057495
    },
    {
        "Hardware": "AMD Radeon(TM) 780M",
        "Name": "D3D Copy",
        "Type": "Load",
        "Value": 0.37013545632362366
    },
    {
        "Hardware": "AMD Radeon(TM) 780M",
        "Name": "D3D Compute 0",
        "Type": "Load",
        "Value": 0.0
    },
    {
        "Hardware": "AMD Radeon(TM) 780M",
        "Name": "D3D Compute 1",
        "Type": "Load",
        "Value": 0.0
    },
    {
        "Hardware": "AMD Radeon(TM) 780M",
        "Name": "D3D Timer 0",
        "Type": "Load",
        "Value": 0.0
    },
    {
        "Hardware": "AMD Radeon(TM) 780M",
        "Name": "D3D Security 1",
        "Type": "Load",
        "Value": 0.0
    },
    {
        "Hardware": "AMD Radeon(TM) 780M",
        "Name": "D3D High Priority Compute",
        "Type": "Load",
        "Value": 0.0
    },
    {
        "Hardware": "AMD Radeon(TM) 780M",
        "Name": "D3D High Priority 3D",
        "Type": "Load",
        "Value": 0.0
    },
    {
        "Hardware": "AMD Radeon(TM) 780M",
        "Name": "D3D Video JPEG 0",
        "Type": "Load",
        "Value": 0.0
    },
    {
        "Hardware": "AMD Radeon(TM) 780M",
        "Name": "D3D Video Codec 0",
        "Type": "Load",
        "Value": 0.0
    },
    {
        "Hardware": "AMD Radeon(TM) 780M",
        "Name": "GPU Memory Used",
        "Type": "SmallData",
        "Value": 1710.0
    },
    {
        "Hardware": "AMD Radeon(TM) 780M",
        "Name": "GPU Memory Free",
        "Type": "SmallData",
        "Value": 2386.0
    },
    {
        "Hardware": "AMD Radeon(TM) 780M",
        "Name": "GPU Core",
        "Type": "Clock",
        "Value": 800.0
    },
    {
        "Hardware": "AMD Radeon(TM) 780M",
        "Name": "GPU SoC",
        "Type": "Clock",
        "Value": 400.0
    },
    {
        "Hardware": "AMD Radeon(TM) 780M",
        "Name": "GPU Memory",
        "Type": "Clock",
        "Value": 2800.0
    },
    {
        "Hardware": "AMD Radeon(TM) 780M",
        "Name": "GPU VR SoC",
        "Type": "Temperature",
        "Value": 43.0
    },
    {
        "Hardware": "AMD Radeon(TM) 780M",
        "Name": "GPU Core",
        "Type": "Voltage",
        "Value": 0.7150000333786011
    },
    {
        "Hardware": "AMD Radeon(TM) 780M",
        "Name": "GPU SoC",
        "Type": "Voltage",
        "Value": 0.9740000367164612
    },
    {
        "Hardware": "AMD Radeon(TM) 780M",
        "Name": "GPU Core",
        "Type": "Load",
        "Value": 1.0
    },
    {
        "Hardware": "AMD Radeon(TM) 780M",
        "Name": "GPU Core",
        "Type": "Power",
        "Value": 2.0
    },
    {
        "Hardware": "AMD Radeon(TM) 780M",
        "Name": "GPU SoC",
        "Type": "Power",
        "Value": 3.0
    },
    {
        "Hardware": "AMD Radeon(TM) RX 7700S",
        "Name": "GPU Memory Total",
        "Type": "SmallData",
        "Value": 8176.0
    },
    {
        "Hardware": "AMD Radeon(TM) RX 7700S",
        "Name": "Fullscreen FPS",
        "Type": "Factor",
        "Value": 0.0
    },
    {
        "Hardware": "AMD Radeon(TM) RX 7700S",
        "Name": "D3D Dedicated Memory Total",
        "Type": "SmallData",
        "Value": 8123.00390625
    },
    {
        "Hardware": "AMD Radeon(TM) RX 7700S",
        "Name": "D3D Dedicated Memory Free",
        "Type": "SmallData",
        "Value": 8120.453125
    },
    {
        "Hardware": "AMD Radeon(TM) RX 7700S",
        "Name": "D3D Dedicated Memory Used",
        "Type": "SmallData",
        "Value": 2.55078125
    },
    {
        "Hardware": "AMD Radeon(TM) RX 7700S",
        "Name": "D3D Shared Memory Used",
        "Type": "SmallData",
        "Value": 2.0
    },
    {
        "Hardware": "AMD Radeon(TM) RX 7700S",
        "Name": "D3D Shared Memory Free",
        "Type": "SmallData",
        "Value": 14236.431640625
    },
    {
        "Hardware": "AMD Radeon(TM) RX 7700S",
        "Name": "D3D Shared Memory Total",
        "Type": "SmallData",
        "Value": 14238.431640625
    },
    {
        "Hardware": "AMD Radeon(TM) RX 7700S",
        "Name": "D3D 3D",
        "Type": "Load",
        "Value": 0.0
    },
    {
        "Hardware": "AMD Radeon(TM) RX 7700S",
        "Name": "D3D Copy",
        "Type": "Load",
        "Value": 0.0
    },
    {
        "Hardware": "AMD Radeon(TM) RX 7700S",
        "Name": "D3D Compute 0",
        "Type": "Load",
        "Value": 0.0
    },
    {
        "Hardware": "AMD Radeon(TM) RX 7700S",
        "Name": "D3D Copy",
        "Type": "Load",
        "Value": 0.0
    },
    {
        "Hardware": "AMD Radeon(TM) RX 7700S",
        "Name": "D3D Timer 0",
        "Type": "Load",
        "Value": 0.0
    },
    {
        "Hardware": "AMD Radeon(TM) RX 7700S",
        "Name": "D3D Security 1",
        "Type": "Load",
        "Value": 0.0
    },
    {
        "Hardware": "AMD Radeon(TM) RX 7700S",
        "Name": "D3D Video JPEG 0",
        "Type": "Load",
        "Value": 0.0
    },
    {
        "Hardware": "AMD Radeon(TM) RX 7700S",
        "Name": "D3D Video Codec Engine",
        "Type": "Load",
        "Value": 0.0
    },
    {
        "Hardware": "AMD Radeon(TM) RX 7700S",
        "Name": "GPU Memory Used",
        "Type": "SmallData",
        "Value": 2.0
    },
    {
        "Hardware": "AMD Radeon(TM) RX 7700S",
        "Name": "GPU Memory Free",
        "Type": "SmallData",
        "Value": 8174.0
    },
    {
        "Hardware": "AMD Radeon(TM) RX 7700S",
        "Name": "GPU Core",
        "Type": "Clock",
        "Value": 0.0
    },
    {
        "Hardware": "AMD Radeon(TM) RX 7700S",
        "Name": "GPU Memory",
        "Type": "Clock",
        "Value": 2.0
    },
    {
        "Hardware": "AMD Radeon(TM) RX 7700S",
        "Name": "GPU Core",
        "Type": "Temperature",
        "Value": 47.0
    },
    {
        "Hardware": "AMD Radeon(TM) RX 7700S",
        "Name": "GPU Memory",
        "Type": "Temperature",
        "Value": 56.0
    },
    {
        "Hardware": "AMD Radeon(TM) RX 7700S",
        "Name": "GPU Hot Spot",
        "Type": "Temperature",
        "Value": 48.0
    },
    {
        "Hardware": "AMD Radeon(TM) RX 7700S",
        "Name": "GPU Fan",
        "Type": "Fan",
        "Value": 0.0
    },
    {
        "Hardware": "AMD Radeon(TM) RX 7700S",
        "Name": "GPU Fan",
        "Type": "Control",
        "Value": 30.0
    },
    {
        "Hardware": "AMD Radeon(TM) RX 7700S",
        "Name": "GPU Core",
        "Type": "Voltage",
        "Value": 0.018000001087784767
    },
    {
        "Hardware": "AMD Radeon(TM) RX 7700S",
        "Name": "GPU Core",
        "Type": "Load",
        "Value": 0.0
    },
    {
        "Hardware": "AMD Radeon(TM) RX 7700S",
        "Name": "GPU Memory",
        "Type": "Load",
        "Value": 0.0
    },
    {
        "Hardware": "Corsair MP600 CORE MINI",
        "Name": "Temperature",
        "Type": "Temperature",
        "Value": 37.0
    },
    {
        "Hardware": "Corsair MP600 CORE MINI",
        "Name": "Available Spare",
        "Type": "Level",
        "Value": 100.0
    },
    {
        "Hardware": "Corsair MP600 CORE MINI",
        "Name": "Available Spare Threshold",
        "Type": "Level",
        "Value": 5.0
    },
    {
        "Hardware": "Corsair MP600 CORE MINI",
        "Name": "Percentage Used",
        "Type": "Level",
        "Value": 4.0
    },
    {
        "Hardware": "Corsair MP600 CORE MINI",
        "Name": "Data Read",
        "Type": "Data",
        "Value": 5237.0
    },
    {
        "Hardware": "Corsair MP600 CORE MINI",
        "Name": "Data Written",
        "Type": "Data",
        "Value": 10224.0
    },
    {
        "Hardware": "Corsair MP600 CORE MINI",
        "Name": "Temperature 1",
        "Type": "Temperature",
        "Value": 37.0
    },
    {
        "Hardware": "Corsair MP600 CORE MINI",
        "Name": "Used Space",
        "Type": "Load",
        "Value": 12.48919677734375
    },
    {
        "Hardware": "Corsair MP600 CORE MINI",
        "Name": "Read Activity",
        "Type": "Load",
        "Value": 7.584113121032715
    },
    {
        "Hardware": "Corsair MP600 CORE MINI",
        "Name": "Write Activity",
        "Type": "Load",
        "Value": 1.2726794481277466
    },
    {
        "Hardware": "Corsair MP600 CORE MINI",
        "Name": "Total Activity",
        "Type": "Load",
        "Value": 8.132360458374023
    },
    {
        "Hardware": "Corsair MP600 CORE MINI",
        "Name": "Read Rate",
        "Type": "Throughput",
        "Value": 10643170.0
    },
    {
        "Hardware": "Corsair MP600 CORE MINI",
        "Name": "Write Rate",
        "Type": "Throughput",
        "Value": 699791.5
    },
    {
        "Hardware": "WD_BLACK SN850X 1000GB",
        "Name": "Temperature",
        "Type": "Temperature",
        "Value": 37.0
    },
    {
        "Hardware": "WD_BLACK SN850X 1000GB",
        "Name": "Available Spare",
        "Type": "Level",
        "Value": 100.0
    },
    {
        "Hardware": "WD_BLACK SN850X 1000GB",
        "Name": "Available Spare Threshold",
        "Type": "Level",
        "Value": 10.0
    },
    {
        "Hardware": "WD_BLACK SN850X 1000GB",
        "Name": "Percentage Used",
        "Type": "Level",
        "Value": 1.0
    },
    {
        "Hardware": "WD_BLACK SN850X 1000GB",
        "Name": "Data Read",
        "Type": "Data",
        "Value": 10034.0
    },
    {
        "Hardware": "WD_BLACK SN850X 1000GB",
        "Name": "Data Written",
        "Type": "Data",
        "Value": 10625.0
    },
    {
        "Hardware": "WD_BLACK SN850X 1000GB",
        "Name": "Used Space",
        "Type": "Load",
        "Value": 26.9981689453125
    },
    {
        "Hardware": "WD_BLACK SN850X 1000GB",
        "Name": "Read Activity",
        "Type": "Load",
        "Value": 0.6328736543655396
    },
    {
        "Hardware": "WD_BLACK SN850X 1000GB",
        "Name": "Write Activity",
        "Type": "Load",
        "Value": 4.44479513168335
    },
    {
        "Hardware": "WD_BLACK SN850X 1000GB",
        "Name": "Total Activity",
        "Type": "Load",
        "Value": 3.970041036605835
    },
    {
        "Hardware": "WD_BLACK SN850X 1000GB",
        "Name": "Read Rate",
        "Type": "Throughput",
        "Value": 196485.28125
    },
    {
        "Hardware": "WD_BLACK SN850X 1000GB",
        "Name": "Write Rate",
        "Type": "Throughput",
        "Value": 2759328.0
    },
    {
        "Hardware": "Bluetooth Network Connection",
        "Name": "Data Uploaded",
        "Type": "Data",
        "Value": 0.0
    },
    {
        "Hardware": "Bluetooth Network Connection",
        "Name": "Data Downloaded",
        "Type": "Data",
        "Value": 0.0
    },
    {
        "Hardware": "Bluetooth Network Connection",
        "Name": "Upload Speed",
        "Type": "Throughput",
        "Value": 0.0
    },
    {
        "Hardware": "Bluetooth Network Connection",
        "Name": "Download Speed",
        "Type": "Throughput",
        "Value": 0.0
    },
    {
        "Hardware": "Bluetooth Network Connection",
        "Name": "Network Utilization",
        "Type": "Load",
        "Value": 0.0
    },
    {
        "Hardware": "Ethernet 2",
        "Name": "Data Uploaded",
        "Type": "Data",
        "Value": 0.0
    },
    {
        "Hardware": "Ethernet 2",
        "Name": "Data Downloaded",
        "Type": "Data",
        "Value": 0.0
    },
    {
        "Hardware": "Ethernet 2",
        "Name": "Upload Speed",
        "Type": "Throughput",
        "Value": 0.0
    },
    {
        "Hardware": "Ethernet 2",
        "Name": "Download Speed",
        "Type": "Throughput",
        "Value": 0.0
    },
    {
        "Hardware": "Ethernet 2",
        "Name": "Network Utilization",
        "Type": "Load",
        "Value": 0.0
    },
    {
        "Hardware": "Local Area Connection* 10",
        "Name": "Data Uploaded",
        "Type": "Data",
        "Value": 0.0
    },
    {
        "Hardware": "Local Area Connection* 10",
        "Name": "Data Downloaded",
        "Type": "Data",
        "Value": 0.0
    },
    {
        "Hardware": "Local Area Connection* 10",
        "Name": "Upload Speed",
        "Type": "Throughput",
        "Value": 0.0
    },
    {
        "Hardware": "Local Area Connection* 10",
        "Name": "Download Speed",
        "Type": "Throughput",
        "Value": 0.0
    },
    {
        "Hardware": "Local Area Connection* 10",
        "Name": "Network Utilization",
        "Type": "Load",
        "Value": 0.0
    },
    {
        "Hardware": "Local Area Connection* 9",
        "Name": "Data Uploaded",
        "Type": "Data",
        "Value": 0.0
    },
    {
        "Hardware": "Local Area Connection* 9",
        "Name": "Data Downloaded",
        "Type": "Data",
        "Value": 0.0
    },
    {
        "Hardware": "Local Area Connection* 9",
        "Name": "Upload Speed",
        "Type": "Throughput",
        "Value": 0.0
    },
    {
        "Hardware": "Local Area Connection* 9",
        "Name": "Download Speed",
        "Type": "Throughput",
        "Value": 0.0
    },
    {
        "Hardware": "Local Area Connection* 9",
        "Name": "Network Utilization",
        "Type": "Load",
        "Value": 0.0
    },
    {
        "Hardware": "Wi-Fi",
        "Name": "Data Uploaded",
        "Type": "Data",
        "Value": 0.031154293566942215
    },
    {
        "Hardware": "Wi-Fi",
        "Name": "Data Downloaded",
        "Type": "Data",
        "Value": 0.3985125422477722
    },
    {
        "Hardware": "Wi-Fi",
        "Name": "Upload Speed",
        "Type": "Throughput",
        "Value": 583.7440795898438
    },
    {
        "Hardware": "Wi-Fi",
        "Name": "Download Speed",
        "Type": "Throughput",
        "Value": 4809.43994140625
    },
    {
        "Hardware": "Wi-Fi",
        "Name": "Network Utilization",
        "Type": "Load",
        "Value": 0.0035924622789025307
    }
]