[
    {
        "Hardware": "AMD Ryzen 7 7840HS w/ Radeon 780M Graphics",
        "Name": "CPU Core #1",
        "Type": "Load",
        "Value": 5.602842330932617
    },
    {
        "Hardware": "AMD Ryzen 7 7840HS w/ Radeon 780M Graphics",
        "Name": "CPU Core #2",
        "Type": "Load",
        "Value": 2.4570107460021973
    },
    {
        "Hardware": "AMD Ryzen 7 7840HS w/ Radeon 780M Graphics",
        "Name": "CPU Core #3",
        "Type": "Load",
        "Value": 10.150837898254395
    },
    {
        "Hardware": "AMD Ryzen 7 7840HS w/ Radeon 780M Graphics",
        "Name": "CPU Core #4",
        "Type": "Load",
        "Value": 7.401508331298828
    },
    {
        "Hardware": "AMD Ryzen 7 7840HS w/ Radeon 780M Graphics",
        "Name": "CPU Core #5",
        "Type": "Load",
        "Value": 0.4887700080871582
    },
    {
        "Hardware": "AMD Ryzen 7 7840HS w/ Radeon 780M Graphics",
        "Name": "CPU Core #6",
        "Type": "Load",
        "Value": 0.29091835021972656
    },
    {
        "Hardware": "AMD Ryzen 7 7840HS w/ Radeon 780M Graphics",
        "Name": "CPU Core #7",
        "Type": "Load",
        "Value": 12.127023696899414
    },
    {
        "Hardware": "AMD Ryzen 7 7840HS w/ Radeon 780M Graphics",
        "Name": "CPU Core #8",
        "Type": "Load",
        "Value": 9.058600425720215
    },
    {
        "Hardware": "AMD Ryzen 7 7840HS w/ Radeon 780M Graphics",
        "Name": "CPU Core #9",
        "Type": "Load",
        "Value": 0.6497025489807129
    },
    {
        "Hardware": "AMD Ryzen 7 7840HS w/ Radeon 780M Graphics",
        "Name": "CPU Core #10",
        "Type": "Load",
        "Value": 0.6781935691833496
    },
    {
        "Hardware": "AMD Ryzen 7 7840HS w/ Radeon 780M Graphics",
        "Name": "CPU Core #11",
        "Type": "Load",
        "Value": 1.7135918140411377
    },
    {
        "Hardware": "AMD Ryzen 7 7840HS w/ Radeon 780M Graphics",
        "Name": "CPU Core #12",
        "Type": "Load",
        "Value": 0.8204996585845947
    },
    {
        "Hardware": "AMD Ryzen 7 7840HS w/ Radeon 780M Graphics",
        "Name": "CPU Core #13",
        "Type": "Load",
        "Value": 5.124240875244141
    },
    {
        "Hardware": "AMD Ryzen 7 7840HS w/ Radeon 780M Graphics",
        "Name": "CPU Core #14",
        "Type": "Load",
        "Value": 3.7647485733032227
    },
    {
        "Hardware": "AMD Ryzen 7 7840HS w/ Radeon 780M Graphics",
        "Name": "CPU Core #15",
        "Type": "Load",
        "Value": 3.12345027923584
    },
    {
        "Hardware": "AMD Ryzen 7 7840HS w/ Radeon 780M Graphics",
        "Name": "CPU Core #16",
        "Type": "Load",
        "Value": 2.205526828765869
    },
    {
        "Hardware": "AMD Ryzen 7 7840HS w/ Radeon 780M Graphics",
        "Name": "CPU Total",
        "Type": "Load",
        "Value": 4.103594779968262
    },
    {
        "Hardware": "AMD Ryzen 7 7840HS w/ Radeon 780M Graphics",
        "Name": "CPU Core Max",
        "Type": "Load",
        "Value": 12.127023696899414
    },
    {
        "Hardware": "AMD Ryzen 7 7840HS w/ Radeon 780M Graphics",
        "Name": "Package",
        "Type": "Power",
        "Value": 12.322325706481934
    },
    {
        "Hardware": "AMD Ryzen 7 7840HS w/ Radeon 780M Graphics",
        "Name": "Core #1",
        "Type": "Clock",
        "Value": 1330.84912109375
    },
    {
        "Hardware": "AMD Ryzen 7 7840HS w/ Radeon 780M Graphics",
        "Name": "Core #1",
        "Type": "Factor",
        "Value": 13.333333015441895
    },
    {
        "Hardware": "AMD Ryzen 7 7840HS w/ Radeon 780M Graphics",
        "Name": "Core #1 (SMU)",
        "Type": "Power",
        "Value": 0.2275814712047577
    },
    {
        "Hardware": "AMD Ryzen 7 7840HS w/ Radeon 780M Graphics",
        "Name": "Core #1 VID",
        "Type": "Voltage",
        "Value": 0.9624999761581421
    },
    {
        "Hardware": "AMD Ryzen 7 7840HS w/ Radeon 780M Graphics",
        "Name": "Core #2",
        "Type": "Clock",
        "Value": 1330.84912109375
    },
    {
        "Hardware": "AMD Ryzen 7 7840HS w/ Radeon 780M Graphics",
        "Name": "Core #2",
        "Type": "Factor",
        "Value": 13.333333015441895
    },
    {
        "Hardware": "AMD Ryzen 7 7840HS w/ Radeon 780M Graphics",
        "Name": "Core #2 (SMU)",
        "Type": "Power",
        "Value": 0.5800409913063049
    },
    {
        "Hardware": "AMD Ryzen 7 7840HS w/ Radeon 780M Graphics",
        "Name": "Core #2 VID",
        "Type": "Voltage",
        "Value": 0.9624999761581421
    },
    {
        "Hardware": "AMD Ryzen 7 7840HS w/ Radeon 780M Graphics",
        "Name": "Core #3",
        "Type": "Clock",
        "Value": 1330.84912109375
    },
    {
        "Hardware": "AMD Ryzen 7 7840HS w/ Radeon 780M Graphics",
        "Name": "Core #3",
        "Type": "Factor",
        "Value": 13.333333015441895
    },
    {
        "Hardware": "AMD Ryzen 7 7840HS w/ Radeon 780M Graphics",
        "Name": "Core #3 (SMU)",
        "Type": "Power",
        "Value": 0.02728150226175785
    },
    {
        "Hardware": "AMD Ryzen 7 7840HS w/ Radeon 780M Graphics",
        "Name": "Core #3 VID",
        "Type": "Voltage",
        "Value": 0.9624999761581421
    },
    {
        "Hardware": "AMD Ryzen 7 7840HS w/ Radeon 780M Graphics",
        "Name": "Core #4",
        "Type": "Clock",
        "Value": 1996.273681640625
    },
    {
        "Hardware": "AMD Ryzen 7 7840HS w/ Radeon 780M Graphics",
        "Name": "Core #4",
        "Type": "Factor",
        "Value": 20.0
    },
    {
        "Hardware": "AMD Ryzen 7 7840HS w/ Radeon 780M Graphics",
        "Name": "Core #4 (SMU)",
        "Type": "Power",
        "Value": 0.6549029350280762
    },
    {
        "Hardware": "AMD Ryzen 7 7840HS w/ Radeon 780M Graphics",
        "Name": "Core #4 VID",
        "Type": "Voltage",
        "Value": 0.9624999761581421
    },
    {
        "Hardware": "AMD Ryzen 7 7840HS w/ Radeon 780M Graphics",
        "Name": "Core #5",
        "Type": "Clock",
        "Value": 1330.84912109375
    },
    {
        "Hardware": "AMD Ryzen 7 7840HS w/ Radeon 780M Graphics",
        "Name": "Core #5",
        "Type": "Factor",
        "Value": 13.333333015441895
    },
    {
        "Hardware": "AMD Ryzen 7 7840HS w/ Radeon 780M Graphics",
        "Name": "Core #5 (SMU)",
        "Type": "Power",
        "Value": 0.04724081605672836
    },
    {
        "Hardware": "AMD Ryzen 7 7840HS w/ Radeon 780M Graphics",
        "Name": "Core #5 VID",
        "Type": "Voltage",
        "Value": 0.9624999761581421
    },
    {
        "Hardware": "AMD Ryzen 7 7840HS w/ Radeon 780M Graphics",
        "Name": "Core #6",
        "Type": "Clock",
        "Value": 1330.84912109375
    },
    {
        "Hardware": "AMD Ryzen 7 7840HS w/ Radeon 780M Graphics",
        "Name": "Core #6",
        "Type": "Factor",
        "Value": 13.333333015441895
    },
    {
        "Hardware": "AMD Ryzen 7 7840HS w/ Radeon 780M Graphics",
        "Name": "Core #6 (SMU)",
        "Type": "Power",
        "Value": 0.0880284383893013
    },
    {
        "Hardware": "AMD Ryzen 7 7840HS w/ Radeon 780M Graphics",
        "Name": "Core #6 VID",
        "Type": "Voltage",
        "Value": 0.9624999761581421
    },
    {
        "Hardware": "AMD Ryzen 7 7840HS w/ Radeon 780M Graphics",
        "Name": "Core #7",
        "Type": "Clock",
        "Value": 1330.84912109375
    },
    {
        "Hardware": "AMD Ryzen 7 7840HS w/ Radeon 780M Graphics",
        "Name": "Core #7",
        "Type": "Factor",
        "Value": 13.333333015441895
    },
    {
        "Hardware": "AMD Ryzen 7 7840HS w/ Radeon 780M Graphics",
        "Name": "Core #7 (SMU)",
        "Type": "Power",
        "Value": 0.2967062294483185
    },
    {
        "Hardware": "AMD Ryzen 7 7840HS w/ Radeon 780M Graphics",
        "Name": "Core #7 VID",
        "Type": "Voltage",
        "Value": 0.9624999761581421
    },
    {
        "Hardware": "AMD Ryzen 7 7840HS w/ Radeon 780M Graphics",
        "Name": "Core #8",
        "Type": "Clock",
        "Value": 1330.84912109375
    },
    {
        "Hardware": "AMD Ryzen 7 7840HS w/ Radeon 780M Graphics",
        "Name": "Core #8",
        "Type": "Factor",
        "Value": 13.333333015441895
    },
    {
        "Hardware": "AMD Ryzen 7 7840HS w/ Radeon 780M Graphics",
        "Name": "Core #8 (SMU)",
        "Type": "Power",
        "Value": 0.1618531197309494
    },
    {
        "Hardware": "AMD Ryzen 7 7840HS w/ Radeon 780M Graphics",
        "Name": "Core #8 VID",
        "Type": "Voltage",
        "Value": 0.9624999761581421
    },
    {
        "Hardware": "AMD Ryzen 7 7840HS w/ Radeon 780M Graphics",
        "Name": "Core (Tctl/Tdie)",
        "Type": "Temperature",
        "Value": 47.75000762939453
    },
    {
        "Hardware": "AMD Ryzen 7 7840HS w/ Radeon 780M Graphics",
        "Name": "Core (SVI2 TFN)",
        "Type": "Voltage",
        "Value": 1.5499999523162842
    },
    {
        "Hardware": "AMD Ryzen 7 7840HS w/ Radeon 780M Graphics",
        "Name": "SoC (SVI2 TFN)",
        "Type": "Voltage",
        "Value": 1.5499999523162842
    },
    {
        "Hardware": "AMD Ryzen 7 7840HS w/ Radeon 780M Graphics",
        "Name": "Bus Speed",
        "Type": "Clock",
        "Value": 99.81368255615234
    },
    {
        "Hardware": "Generic Memory",
        "Name": "Memory Used",
        "Type": "Data",
        "Value": 8.79229736328125
    },
    {
        "Hardware": "Generic Memory",
        "Name": "Memory Available",
        "Type": "Data",
        "Value": 19.017139434814453
    },
    {
        "Hardware": "Generic Memory",
        "Name": "Memory",
        "Type": "Load",
        "Value": 31.616233825683594
    },
    {
        "Hardware": "Generic Memory",
        "Name": "Virtual Memory Used",
        "Type": "Data",
        "Value": 13.496353149414062
    },
    {
        "Hardware": "Generic Memory",
        "Name": "Virtual Memory Available",
        "Type": "Data",
        "Value": 18.81308364868164
    },
    {
        "Hardware": "Generic Memory",
        "Name": "Virtual Memory",
        "Type": "Load",
        "Value": 41.77217102050781
    },
    {
        "Hardware": "AMD Radeon(TM) 780M",
        "Name": "GPU Memory Total",
        "Type": "SmallData",
        "Value": 4096.0
    },
    {
        "Hardware": "AMD Radeon(TM) 780M",
        "Name": "Fullscreen FPS",
        "Type": "Factor",
        "Value": 0.0
    },
    {
        "Hardware": "AMD Radeon(TM) 780M",
        "Name": "D3D Dedicated Memory Total",
        "Type": "SmallData",
        "Value": 3949.22265625
    },
    {
        "Hardware": "AMD Radeon(TM) 780M",
        "Name": "D3D Dedicated Memory Free",
        "Type": "SmallData",
        "Value": 2560.72265625
    },
    {
        "Hardware": "AMD Radeon(TM) 780M",
        "Name": "D3D Dedicated Memory Used",
        "Type": "SmallData",
        "Value": 1388.5
    },
    {
        "Hardware": "AMD Radeon(TM) 780M",
        "Name": "D3D Shared Memory Used",
        "Type": "SmallData",
        "Value": 707.62890625
    },
    {
        "Hardware": "AMD Radeon(TM) 780M",
        "Name": "D3D Shared Memory Free",
        "Type": "SmallData",
        "Value": 13530.802734375
    },
    {
        "Hardware": "AMD Radeon(TM) 780M",
        "Name": "D3D Shared Memory Total",
        "Type": "SmallData",
        "Value": 14238.431640625
    },
    {
        "Hardware": "AMD Radeon(TM) 780M",
        "Name": "D3D 3D",
        "Type": "Load",
        "Value": 3.699798345565796
    },
    {
        "Hardware": "AMD Radeon(TM) 780M",
        "Name": "D3D Copy",
        "Type": "Load",
        "Value": 0.20871084928512573
    },
    {
        "Hardware": "AMD Radeon(TM) 780M",
        "Name": "D3D Compute 0",
        "Type": "Load",
        "Value": 0.0
    },
    {
        "Hardware": "AMD Radeon(TM) 780M",
        "Name": "D3D Compute 1",
        "Type": "Load",
        "Value": 0.0
    },
    {
        "Hardware": "AMD Radeon(TM) 780M",
        "Name": "D3D Timer 0",
        "Type": "Load",
        "Value": 0.15161389112472534
    },
    {
        "Hardware": "AMD Radeon(TM) 780M",
        "Name": "D3D Security 1",
        "Type": "Load",
        "Value": 0.0
    },
    {
        "Hardware": "AMD Radeon(TM) 780M",
        "Name": "D3D High Priority Compute",
        "Type": "Load",
        "Value": 0.0
    },
    {
        "Hardware": "AMD Radeon(TM) 780M",
        "Name": "D3D High Priority 3D",
        "Type": "Load",
        "Value": 0.0
    },
    {
        "Hardware": "AMD Radeon(TM) 780M",
        "Name": "D3D Video JPEG 0",
        "Type": "Load",
        "Value": 0.0
    },
    {
        "Hardware": "AMD Radeon(TM) 780M",
        "Name": "D3D Video Codec 0",
        "Type": "Load",
        "Value": 0.0
    },
    {
        "Hardware": "AMD Radeon(TM) 780M",
        "Name": "GPU Memory Used",
        "Type": "SmallData",
        "Value": 1388.0
    },
    {
        "Hardware": "AMD Radeon(TM) 780M",
        "Name": "GPU Memory Free",
        "Type": "SmallData",
        "Value": 2708.0
    },
    {
        "Hardware": "AMD Radeon(TM) 780M",
        "Name": "GPU Core",
        "Type": "Clock",
        "Value": 800.0
    },
    {
        "Hardware": "AMD Radeon(TM) 780M",
        "Name": "GPU SoC",
        "Type": "Clock",
        "Value": 400.0
    },
    {
        "Hardware": "AMD Radeon(TM) 780M",
        "Name": "GPU Memory",
        "Type": "Clock",
        "Value": 2800.0
    },
    {
        "Hardware": "AMD Radeon(TM) 780M",
        "Name": "GPU VR SoC",
        "Type": "Temperature",
        "Value": 47.0
    },
    {
        "Hardware": "AMD Radeon(TM) 780M",
        "Name": "GPU Core",
        "Type": "Voltage",
        "Value": 0.984000027179718
    },
    {
        "Hardware": "AMD Radeon(TM) 780M",
        "Name": "GPU SoC",
        "Type": "Voltage",
        "Value": 0.9740000367164612
    },
    {
        "Hardware": "AMD Radeon(TM) 780M",
        "Name": "GPU Core",
        "Type": "Load",
        "Value": 1.0
    },
    {
        "Hardware": "AMD Radeon(TM) 780M",
        "Name": "GPU Core",
        "Type": "Power",
        "Value": 1.0
    },
    {
        "Hardware": "AMD Radeon(TM) 780M",
        "Name": "GPU SoC",
        "Type": "Power",
        "Value": 3.0
    },
    {
        "Hardware": "AMD Radeon(TM) RX 7700S",
        "Name": "GPU Memory Total",
        "Type": "SmallData",
        "Value": 8176.0
    },
    {
        "Hardware": "AMD Radeon(TM) RX 7700S",
        "Name": "Fullscreen FPS",
        "Type": "Factor",
        "Value": 0.0
    },
    {
        "Hardware": "AMD Radeon(TM) RX 7700S",
        "Name": "D3D Dedicated Memory Total",
        "Type": "SmallData",
        "Value": 8123.00390625
    },
    {
        "Hardware": "AMD Radeon(TM) RX 7700S",
        "Name": "D3D Dedicated Memory Free",
        "Type": "SmallData",
        "Value": 8120.453125
    },
    {
        "Hardware": "AMD Radeon(TM) RX 7700S",
        "Name": "D3D Dedicated Memory Used",
        "Type": "SmallData",
        "Value": 2.55078125
    },
    {
        "Hardware": "AMD Radeon(TM) RX 7700S",
        "Name": "D3D Shared Memory Used",
        "Type": "SmallData",
        "Value": 2.0
    },
    {
        "Hardware": "AMD Radeon(TM) RX 7700S",
        "Name": "D3D Shared Memory Free",
        "Type": "SmallData",
        "Value": 14236.431640625
    },
    {
        "Hardware": "AMD Radeon(TM) RX 7700S",
        "Name": "D3D Shared Memory Total",
        "Type": "SmallData",
        "Value": 14238.431640625
    },
    {
        "Hardware": "AMD Radeon(TM) RX 7700S",
        "Name": "D3D 3D",
        "Type": "Load",
        "Value": 0.0
    },
    {
        "Hardware": "AMD Radeon(TM) RX 7700S",
        "Name": "D3D Copy",
        "Type": "Load",
        "Value": 0.0
    },
    {
        "Hardware": "AMD Radeon(TM) RX 7700S",
        "Name": "D3D Compute 0",
        "Type": "Load",
        "Value": 0.0
    },
    {
        "Hardware": "AMD Radeon(TM) RX 7700S",
        "Name": "D3D Copy",
        "Type": "Load",
        "Value": 0.0
    },
    {
        "Hardware": "AMD Radeon(TM) RX 7700S",
        "Name": "D3D Timer 0",
        "Type": "Load",
        "Value": 0.0
    },
    {
        "Hardware": "AMD Radeon(TM) RX 7700S",
        "Name": "D3D Security 1",
        "Type": "Load",
        "Value": 0.0
    },
    {
        "Hardware": "AMD Radeon(TM) RX 7700S",
        "Name": "D3D Video JPEG 0",
        "Type": "Load",
        "Value": 0.0
    },
    {
        "Hardware": "AMD Radeon(TM) RX 7700S",
        "Name": "D3D Video Codec Engine",
        "Type": "Load",
        "Value": 0.0
    },
    {
        "Hardware": "AMD Radeon(TM) RX 7700S",
        "Name": "GPU Memory Used",
        "Type": "SmallData",
        "Value": 2.0
    },
    {
        "Hardware": "AMD Radeon(TM) RX 7700S",
        "Name": "GPU Memory Free",
        "Type": "SmallData",
        "Value": 8174.0
    },
    {
        "Hardware": "AMD Radeon(TM) RX 7700S",
        "Name": "GPU Core",
        "Type": "Clock",
        "Value": 0.0
    },
    {
        "Hardware": "AMD Radeon(TM) RX 7700S",
        "Name": "GPU Memory",
        "Type": "Clock",
        "Value": 2.0
    },
    {
        "Hardware": "AMD Radeon(TM) RX 7700S",
        "Name": "GPU Core",
        "Type": "Temperature",
        "Value": 32.0
    },
    {
        "Hardware": "AMD Radeon(TM) RX 7700S",
        "Name": "GPU Memory",
        "Type": "Temperature",
        "Value": 42.0
    },
    {
        "Hardware": "AMD Radeon(TM) RX 7700S",
        "Name": "GPU Hot Spot",
        "Type": "Temperature",
        "Value": 33.0
    },
    {
        "Hardware": "AMD Radeon(TM) RX 7700S",
        "Name": "GPU Fan",
        "Type": "Fan",
        "Value": 0.0
    },
    {
        "Hardware": "AMD Radeon(TM) RX 7700S",
        "Name": "GPU Fan",
        "Type": "Control",
        "Value": 30.0
    },
    {
        "Hardware": "AMD Radeon(TM) RX 7700S",
        "Name": "GPU Core",
        "Type": "Voltage",
        "Value": 0.018000001087784767
    },
    {
        "Hardware": "AMD Radeon(TM) RX 7700S",
        "Name": "GPU Core",
        "Type": "Load",
        "Value": 0.0
    },
    {
        "Hardware": "AMD Radeon(TM) RX 7700S",
        "Name": "GPU Memory",
        "Type": "Load",
        "Value": 0.0
    },
    {
        "Hardware": "Corsair MP600 CORE MINI",
        "Name": "Temperature",
        "Type": "Temperature",
        "Value": 46.0
    },
    {
        "Hardware": "Corsair MP600 CORE MINI",
        "Name": "Available Spare",
        "Type": "Level",
        "Value": 100.0
    },
    {
        "Hardware": "Corsair MP600 CORE MINI",
        "Name": "Available Spare Threshold",
        "Type": "Level",
        "Value": 5.0
    },
    {
        "Hardware": "Corsair MP600 CORE MINI",
        "Name": "Percentage Used",
        "Type": "Level",
        "Value": 4.0
    },
    {
        "Hardware": "Corsair MP600 CORE MINI",
        "Name": "Data Read",
        "Type": "Data",
        "Value": 5237.0
    },
    {
        "Hardware": "Corsair MP600 CORE MINI",
        "Name": "Data Written",
        "Type": "Data",
        "Value": 10224.0
    },
    {
        "Hardware": "Corsair MP600 CORE MINI",
        "Name": "Temperature 1",
        "Type": "Temperature",
        "Value": 46.0
    },
    {
        "Hardware": "Corsair MP600 CORE MINI",
        "Name": "Used Space",
        "Type": "Load",
        "Value": 12.545089721679688
    },
    {
        "Hardware": "Corsair MP600 CORE MINI",
        "Name": "Read Activity",
        "Type": "Load",
        "Value": 0.0
    },
    {
        "Hardware": "Corsair MP600 CORE MINI",
        "Name": "Write Activity",
        "Type": "Load",
        "Value": 1.9264088869094849
    },
    {
        "Hardware": "Corsair MP600 CORE MINI",
        "Name": "Total Activity",
        "Type": "Load",
        "Value": 0.6571995615959167
    },
    {
        "Hardware": "Corsair MP600 CORE MINI",
        "Name": "Read Rate",
        "Type": "Throughput",
        "Value": 0.0
    },
    {
        "Hardware": "Corsair MP600 CORE MINI",
        "Name": "Write Rate",
        "Type": "Throughput",
        "Value": 29485.728515625
    },
    {
        "Hardware": "WD_BLACK SN850X 1000GB",
        "Name": "Temperature",
        "Type": "Temperature",
        "Value": 50.0
    },
    {
        "Hardware": "WD_BLACK SN850X 1000GB",
        "Name": "Available Spare",
        "Type": "Level",
        "Value": 100.0
    },
    {
        "Hardware": "WD_BLACK SN850X 1000GB",
        "Name": "Available Spare Threshold",
        "Type": "Level",
        "Value": 10.0
    },
    {
        "Hardware": "WD_BLACK SN850X 1000GB",
        "Name": "Percentage Used",
        "Type": "Level",
        "Value": 1.0
    },
    {
        "Hardware": "WD_BLACK SN850X 1000GB",
        "Name": "Data Read",
        "Type": "Data",
        "Value": 10013.0
    },
    {
        "Hardware": "WD_BLACK SN850X 1000GB",
        "Name": "Data Written",
        "Type": "Data",
        "Value": 10615.0
    },
    {
        "Hardware": "WD_BLACK SN850X 1000GB",
        "Name": "Used Space",
        "Type": "Load",
        "Value": 26.967361450195312
    },
    {
        "Hardware": "WD_BLACK SN850X 1000GB",
        "Name": "Read Activity",
        "Type": "Load",
        "Value": 0.0
    },
    {
        "Hardware": "WD_BLACK SN850X 1000GB",
        "Name": "Write Activity",
        "Type": "Load",
        "Value": 0.11108187586069107
    },
    {
        "Hardware": "WD_BLACK SN850X 1000GB",
        "Name": "Total Activity",
        "Type": "Load",
        "Value": 0.05615418031811714
    },
    {
        "Hardware": "WD_BLACK SN850X 1000GB",
        "Name": "Read Rate",
        "Type": "Throughput",
        "Value": 0.0
    },
    {
        "Hardware": "WD_BLACK SN850X 1000GB",
        "Name": "Write Rate",
        "Type": "Throughput",
        "Value": 13923.818359375
    },
    {
        "Hardware": "Bluetooth Network Connection",
        "Name": "Data Uploaded",
        "Type": "Data",
        "Value": 0.0
    },
    {
        "Hardware": "Bluetooth Network Connection",
        "Name": "Data Downloaded",
        "Type": "Data",
        "Value": 0.0
    },
    {
        "Hardware": "Bluetooth Network Connection",
        "Name": "Upload Speed",
        "Type": "Throughput",
        "Value": 0.0
    },
    {
        "Hardware": "Bluetooth Network Connection",
        "Name": "Download Speed",
        "Type": "Throughput",
        "Value": 0.0
    },
    {
        "Hardware": "Bluetooth Network Connection",
        "Name": "Network Utilization",
        "Type": "Load",
        "Value": 0.0
    },
    {
        "Hardware": "Ethernet 2",
        "Name": "Data Uploaded",
        "Type": "Data",
        "Value": 0.0
    },
    {
        "Hardware": "Ethernet 2",
        "Name": "Data Downloaded",
        "Type": "Data",
        "Value": 0.0
    },
    {
        "Hardware": "Ethernet 2",
        "Name": "Upload Speed",
        "Type": "Throughput",
        "Value": 0.0
    },
    {
        "Hardware": "Ethernet 2",
        "Name": "Download Speed",
        "Type": "Throughput",
        "Value": 0.0
    },
    {
        "Hardware": "Ethernet 2",
        "Name": "Network Utilization",
        "Type": "Load",
        "Value": 0.0
    },
    {
        "Hardware": "Local Area Connection* 10",
        "Name": "Data Uploaded",
        "Type": "Data",
        "Value": 0.0
    },
    {
        "Hardware": "Local Area Connection* 10",
        "Name": "Data Downloaded",
        "Type": "Data",
        "Value": 0.0
    },
    {
        "Hardware": "Local Area Connection* 10",
        "Name": "Upload Speed",
        "Type": "Throughput",
        "Value": 0.0
    },
    {
        "Hardware": "Local Area Connection* 10",
        "Name": "Download Speed",
        "Type": "Throughput",
        "Value": 0.0
    },
    {
        "Hardware": "Local Area Connection* 10",
        "Name": "Network Utilization",
        "Type": "Load",
        "Value": 0.0
    },
    {
        "Hardware": "Local Area Connection* 9",
        "Name": "Data Uploaded",
        "Type": "Data",
        "Value": 0.0
    },
    {
        "Hardware": "Local Area Connection* 9",
        "Name": "Data Downloaded",
        "Type": "Data",
        "Value": 0.0
    },
    {
        "Hardware": "Local Area Connection* 9",
        "Name": "Upload Speed",
        "Type": "Throughput",
        "Value": 0.0
    },
    {
        "Hardware": "Local Area Connection* 9",
        "Name": "Download Speed",
        "Type": "Throughput",
        "Value": 0.0
    },
    {
        "Hardware": "Local Area Connection* 9",
        "Name": "Network Utilization",
        "Type": "Load",
        "Value": 0.0
    },
    {
        "Hardware": "Wi-Fi",
        "Name": "Data Uploaded",
        "Type": "Data",
        "Value": 0.030861884355545044
    },
    {
        "Hardware": "Wi-Fi",
        "Name": "Data Downloaded",
        "Type": "Data",
        "Value": 0.04969625920057297
    },
    {
        "Hardware": "Wi-Fi",
        "Name": "Upload Speed",
        "Type": "Throughput",
        "Value": 680.2180786132812
    },
    {
        "Hardware": "Wi-Fi",
        "Name": "Download Speed",
        "Type": "Throughput",
        "Value": 2999.39794921875
    },
    {
        "Hardware": "Wi-Fi",
        "Name": "Network Utilization",
        "Type": "Load",
        "Value": 0.002451034728437662
    }
]